Workbook

Sheet Gold
A1: sentence | B1: FEATURES | C1: zero-poss | D1: zero-copula | E1: double-tense | F1: be-construction | G1: resultant-done | H1: finna | I1: come | J1: double-modal | K1: multiple-neg | L1: neg-inversion | M1: n-inv-neg-concord | N1: aint | O1: zero-3sg-pres-s | P1: is-was-gen | Q1: zero-pl-s | R1: double-object | S1: wh-qu1 | T1: wh-qu2 | U1: existential-it | V1: demonstrative-them | W1: appositive-pleonastic-pronoun | X1: bin | Y1: verb-stem | Z1: past-tense-swap | AA1: zero-rel-pronoun | AB1: preterite-had | AC1: bare-got
A2: Today's date is October the fourth two thousand seventeen. | B2: {=_xlfn.TEXTJOIN(", ", TRUE, IF(C2:AC2=1, C$1:AC$1, ""))} | C2: 0 | D2: 0 | E2: 0 | F2: 0 | G2: 0 | H2: 0 | I2: 0 | J2: 0 | K2: 0 | L2: 0 | M2: 0 | N2: 0 | O2: 0 | P2: 0 | Q2: 0 | R2: 0 | S2: 0 | T2: 0 | U2: 0 | V2: 0 | W2: 0 | X2: 0 | Y2: 0 | Z2: 0 | AA2: 0 | AB2: 0 | AC2: 0
A3: Birthday is December the first. | B3: {=_xlfn.TEXTJOIN(", ", TRUE, IF(C3:AC3=1, C$1:AC$1, ""))} | C3: 0 | D3: 0 | E3: 0 | F3: 0 | G3: 0 | H3: 0 | I3: 0 | J3: 0 | K3: 0 | L3: 0 | M3: 0 | N3: 0 | O3: 0 | P3: 0 | Q3: 0 | R3: 0 | S3: 0 | T3: 0 | U3: 0 | V3: 0 | W3: 0 | X3: 0 | Y3: 0 | Z3: 0 | AA3: 0 | AB3: 0 | AC3: 0
A4: I was born in Washington DC. | B4: {=_xlfn.TEXTJOIN(", ", TRUE, IF(C4:AC4=1, C$1:AC$1, ""))} | C4: 0 | D4: 0 | E4: 0 | F4: 0 | G4: 0 | H4: 0 | I4: 0 | J4: 0 | K4: 0 | L4: 0 | M4: 0 | N4: 0 | O4: 0 | P4: 0 | Q4: 0 | R4: 0 | S4: 0 | T4: 0 | U4: 0 | V4: 0 | W4: 0 | X4: 0 | Y4: 0 | Z4: 0 | AA4: 0 | AB4: 0 | AC4: 0
A5: Haven't been in that neighborhood in the last four or five years since they, um- It's not the they remodeled. | B5: {=_xlfn.TEXTJOIN(", ", TRUE, IF(C5:AC5=1, C$1:AC$1, ""))} | C5: 0 | D5: 0 | E5: 0 | F5: 0 | G5: 0 | H5: 0 | I5: 0 | J5: 0 | K5: 0 | L5: 0 | M5: 0 | N5: 0 | O5: 0 | P5: 0 | Q5: 0 | R5: 0 | S5: 0 | T5: 0 | U5: 0 | V5: 0 | W5: 0 | X5: 0 | Y5: 0 | Z5: 0 | AA5: 0 | AB5: 0 | AC5: 0
A6: I was born here and then left when I was twenty seven. | B6: {=_xlfn.TEXTJOIN(", ", TRUE, IF(C6:AC6=1, C$1:AC$1, ""))} | C6: 0 | D6: 0 | E6: 0 | F6: 0 | G6: 0 | H6: 0 | I6: 0 | J6: 0 | K6: 0 | L6: 0 | M6: 0 | N6: 0 | O6: 0 | P6: 0 | Q6: 0 | R6: 0 | S6: 0 | T6: 0 | U6: 0 | V6: 0 | W6: 0 | X6: 0 | Y6: 0 | Z6: 0 | AA6: 0 | AB6: 0 | AC6: 0
A7: So I pretty much grew up in DC. | B7: {=_xlfn.TEXTJOIN(", ", TRUE, IF(C7:AC7=1, C$1:AC$1, ""))} | C7: 0 | D7: 0 | E7: 0 | F7: 0 | G7: 0 | H7: 0 | I7: 0 | J7: 0 | K7: 0 | L7: 0 | M7: 0 | N7: 0 | O7: 0 | P7: 0 | Q7: 0 | R7: 0 | S7: 0 | T7: 0 | U7: 0 | V7: 0 | W7: 0 | X7: 0 | Y7: 0 | Z7: 0 | AA7: 0 | AB7: 0 | AC7: 0
A8: I am the director of safety and facilities for RD-WORK-11. | B8: {=_xlfn.TEXTJOIN(", ", TRUE, IF(C8:AC8=1, C$1:AC$1, ""))} | C8: 0 | D8: 0 | E8: 0 | F8: 0 | G8: 0 | H8: 0 | I8: 0 | J8: 0 | K8: 0 | L8: 0 | M8: 0 | N8: 0 | O8: 0 | P8: 0 | Q8: 0 | R8: 0 | S8: 0 | T8: 0 | U8: 0 | V8: 0 | W8: 0 | X8: 0 | Y8: 0 | Z8: 0 | AA8: 0 | AB8: 0 | AC8: 0
A9: Yes, yes, um, for the past four years, I've been catering on the side, for the last four years, yeah. | B9: {=_xlfn.TEXTJOIN(", ", TRUE, IF(C9:AC9=1, C$1:AC$1, ""))} | C9: 0 | D9: 0 | E9: 0 | F9: 0 | G9: 0 | H9: 0 | I9: 0 | J9: 0 | K9: 0 | L9: 0 | M9: 0 | N9: 0 | O9: 0 | P9: 0 | Q9: 0 | R9: 0 | S9: 0 | T9: 0 | U9: 0 | V9: 0 | W9: 0 | X9: 0 | Y9: 0 | Z9: 0 | AA9: 0 | AB9: 0 | AC9: 0
A10: Um, initially when I first started, it was a favor. | B10: {=_xlfn.TEXTJOIN(", ", TRUE, IF(C10:AC10=1, C$1:AC$1, ""))} | C10: 0 | D10: 0 | E10: 0 | F10: 0 | G10: 0 | H10: 0 | I10: 0 | J10: 0 | K10: 0 | L10: 0 | M10: 0 | N10: 0 | O10: 0 | P10: 0 | Q10: 0 | R10: 0 | S10: 0 | T10: 0 | U10: 0 | V10: 0 | W10: 0 | X10: 0 | Y10: 0 | Z10: 0 | AA10: 0 | AB10: 0 | AC10: 0
A11: That's how it started off. | B11: {=_xlfn.TEXTJOIN(", ", TRUE, IF(C11:AC11=1, C$1:AC$1, ""))} | C11: 0 | D11: 0 | E11: 0 | F11: 0 | G11: 0 | H11: 0 | I11: 0 | J11: 0 | K11: 0 | L11: 0 | M11: 0 | N11: 0 | O11: 0 | P11: 0 | Q11: 0 | R11: 0 | S11: 0 | T11: 0 | U11: 0 | V11: 0 | W11: 0 | X11: 0 | Y11: 0 | Z11: 0 | AA11: 0 | AB11: 0 | AC11: 0
A12: Because I always knew I can cook cause my mother's from the south, so. | B12: {=_xlfn.TEXTJOIN(", ", TRUE, IF(C12:AC12=1, C$1:AC$1, ""))} | C12: 0 | D12: 0 | E12: 0 | F12: 0 | G12: 0 | H12: 0 | I12: 0 | J12: 0 | K12: 0 | L12: 0 | M12: 0 | N12: 0 | O12: 0 | P12: 0 | Q12: 0 | R12: 0 | S12: 0 | T12: 0 | U12: 0 | V12: 0 | W12: 0 | X12: 0 | Y12: 0 | Z12: 0 | AA12: 0 | AB12: 0 | AC12: 0
A13: Her southern cooking and my city met. | B13: {=_xlfn.TEXTJOIN(", ", TRUE, IF(C13:AC13=1, C$1:AC$1, ""))} | C13: 0 | D13: 0 | E13: 0 | F13: 0 | G13: 0 | H13: 0 | I13: 0 | J13: 0 | K13: 0 | L13: 0 | M13: 0 | N13: 0 | O13: 0 | P13: 0 | Q13: 0 | R13: 0 | S13: 0 | T13: 0 | U13: 0 | V13: 0 | W13: 0 | X13: 0 | Y13: 0 | Z13: 0 | AA13: 0 | AB13: 0 | AC13: 0
... A716: I love working with kids though. | B716: {=_xlfn.TEXTJOIN(", ", TRUE, IF(C716:AC716=1, C$1:AC$1, ""))} | C716: 0 | D716: 0 | E716: 0 | F716: 0 | G716: 0 | H716: 0 | I716: 0 | J716: 0 | K716: 0 | L716: 0 | M716: 0 | N716: 0 | O716: 0 | P716: 0 | Q716: 0 | R716: 0 | S716: 0 | T716: 0 | U716: 0 | V716: 0 | W716: 0 | X716: 0 | Y716: 0 | Z716: 0 | AA716: 0 | AB716: 0 | AC716: 0

Sheet Sheet1
A1: sentence | B1: count
A2: zero-poss | B2: =COUNTIFS(INDEX(Gold!$A$1:$AC867,0,MATCH(A2,Gold!$1:$1,0)),"1") -> 6
A3: zero-copula | B3: =COUNTIFS(INDEX(Gold!$A$1:$AC868,0,MATCH(A3,Gold!$1:$1,0)),"1") -> 36
A4: double-tense | B4: =COUNTIFS(INDEX(Gold!$A$1:$AC869,0,MATCH(A4,Gold!$1:$1,0)),"1") -> 0
A5: be-construction | B5: =COUNTIFS(INDEX(Gold!$A$1:$AC870,0,MATCH(A5,Gold!$1:$1,0)),"1") -> 3
A6: resultant-done | B6: =COUNTIFS(INDEX(Gold!$A$1:$AC871,0,MATCH(A6,Gold!$1:$1,0)),"1") -> 1
A7: finna | B7: =COUNTIFS(INDEX(Gold!$A$1:$AC872,0,MATCH(A7,Gold!$1:$1,0)),"1") -> 0
A8: come | B8: =COUNTIFS(INDEX(Gold!$A$1:$AC873,0,MATCH(A8,Gold!$1:$1,0)),"1") -> 0
A9: double-modal | B9: =COUNTIFS(INDEX(Gold!$A$1:$AC874,0,MATCH(A9,Gold!$1:$1,0)),"1") -> 0
A10: multiple-neg | B10: =COUNTIFS(INDEX(Gold!$A$1:$AC875,0,MATCH(A10,Gold!$1:$1,0)),"1") -> 19
A11: neg-inversion | B11: =COUNTIFS(INDEX(Gold!$A$1:$AC876,0,MATCH(A11,Gold!$1:$1,0)),"1") -> 1
A12: n-inv-neg-concord | B12: =COUNTIFS(INDEX(Gold!$A$1:$AC877,0,MATCH(A12,Gold!$1:$1,0)),"1") -> 0
A13: aint | B13: =COUNTIFS(INDEX(Gold!$A$1:$AC878,0,MATCH(A13,Gold!$1:$1,0)),"1") -> 7
... A28: bare-got | B28: =COUNTIFS(INDEX(Gold!$A$1:$AC893,0,MATCH(A28,Gold!$1:$1,0)),"1") -> 8
A16384: sentence
A16385: FEATURES
A16386: zero-poss
A16387: zero-copula
A16388: double-tense
A16389: be-construction
A16390: resultant-done
A16391: finna
A16392: come
A16393: double-modal
A16394: multiple-neg
A16395: neg-inversion
... A1032219: preterite-had

Sheet BERT
